ou_sphinx_a11y/__init__.py
ou_sphinx_a11y-0.1.1.dist-info/entry_points.txt
ou_sphinx_a11y-0.1.1.dist-info/WHEEL
ou_sphinx_a11y-0.1.1.dist-info/METADATA
ou_sphinx_a11y-0.1.1.dist-info/RECORD
