Metadata-Version: 2.1
Name: ou-sphinx-a11y
Version: 0.1.1
Summary: 
Author: Mark Hall
Author-email: mark.hall@open.ac.uk
Requires-Python: >=3.8,<4.0
Classifier: Programming Language :: Python :: 3
Classifier: Programming Language :: Python :: 3.10
Classifier: Programming Language :: Python :: 3.8
Classifier: Programming Language :: Python :: 3.9
Requires-Dist: sphinx (>=4.2.0,<6.0.0)
